AUTHORS.rst
CONTRIBUTING.rst
HISTORY.rst
LICENSE
MANIFEST.in
README.rst
setup.cfg
setup.py
docs/Makefile
docs/authors.rst
docs/conf.py
docs/contributing.rst
docs/history.rst
docs/index.rst
docs/installation.rst
docs/make.bat
docs/readme.rst
docs/usage.rst
findifftool/__init__.py
findifftool/attributes.py
findifftool/core.py
findifftool.egg-info/PKG-INFO
findifftool.egg-info/SOURCES.txt
findifftool.egg-info/dependency_links.txt
findifftool.egg-info/not-zip-safe
findifftool.egg-info/top_level.txt
tests/.pytest.restart
tests/__init__.py
tests/test_attributes.py
tests/test_findifftool.py