Metadata-Version: 1.1
Name: findifftool
Version: 0.1.1
Summary: Tools to generate finite difference gradients and Hessians of numerical functions
Home-page: https://github.com/vahtras/findifftool
Author: Olav Vahtras
Author-email: olav.vahtras@gmail.com
License: ISCL
Keywords: findifftool
Platform: UNKNOWN
Classifier: Development Status :: 2 - Pre-Alpha
Classifier: Intended Audience :: Developers
Classifier: License :: OSI Approved :: ISC License (ISCL)
Classifier: Natural Language :: English
Classifier: Programming Language :: Python :: 2
Classifier: Programming Language :: Python :: 2.6
Classifier: Programming Language :: Python :: 2.7
Classifier: Programming Language :: Python :: 3
Classifier: Programming Language :: Python :: 3.3
Classifier: Programming Language :: Python :: 3.4
Classifier: Programming Language :: Python :: 3.5
